{"inkVersion":21,"root":[["\n","ev",{"VAR?":"Suspects"},{"VAR?":"bossMan"},"?","/ev",[{"->":".^.b","c":true},{"b":["^ ","<>","^ Boss Man is currently under suspicion. ","end",{"->":"0.7"},null]}],"nop","^ ","#","^speaker: Player","/#","\n","ev",{"VAR?":"talkedToBossMan"},"/ev",[{"->":".^.b","c":true},{"b":["^ ","<>",{"->":"CanQuestion"},{"->":"0.18"},null]}],[{"->":".^.b"},{"b":[{"->":"Intro"},{"->":"0.18"},null]}],"nop","\n",["done",{"#f":5,"#n":"g-0"}],null],"done",{"Intro":[["<>","^Nice driving, asshole! ","#","^anim: Yelling ","/#","#","^speaker: Boss Man","/#","\n","ev","str","^LÅS UPP SOM SUSPECT","/str",{"VAR?":"debug"},"/ev",{"*":".^.c-0","flg":21},"ev","str","^Thanks.","/str","/ev",{"*":".^.c-1","flg":20},"ev","str","^That wasn't me, it was the other guy.","/str","/ev",{"*":".^.c-2","flg":20},"ev","str","^I gots to go, baby.","/str","/ev",{"*":".^.c-3","flg":20},{"c-0":["\n","ev",{"VAR?":"bossMan"},{"f()":"addsuspect"},"pop","/ev","\n","ev",{"VAR?":"bossManID"},{"x()":"unlockSuspect","exArgs":1},"pop","/ev","\n",{"->":"Intro"},{"#f":5}],"c-1":["\n","^Yeah, real nice... Business is already bad as it is, a totaled car right behind the shop is going to do wonders for the customers. ","#","^anim: Angry ","/#","#","^speaker: Boss Man","/#","\n",{"->":"Intro.IntroCont"},{"#f":5}],"c-2":["\n","^Oh, the other guy. Of course. The one standing here talking to me right now about the other guy. THAT guy. Him. ","#","^anim: Shake","/#","\n",["ev","str","^That's him.","/str","/ev",{"*":".^.c-0","flg":20},"ev","str","^Alright, I did it...","/str","/ev",{"*":".^.c-1","flg":20},{"c-0":["\n","^Alright. Enough of this bit, it was <b>obviously</b> you. ","<>","\n",{"->":"Intro.IntroCont"},{"#f":5}],"c-1":["\n","^Really? I never would've guessed. I could've sworn you said it was the other guy!","\n",{"->":"Intro.IntroCont"},{"#f":5}]}],{"#f":5}],"c-3":["\n","^Go fucking where? Your car is impaled through that tree!","\n","done",{"#f":5}]}],{"IntroCont":[[["ev","visit",2,"MIN","/ev","ev","du",0,"==","/ev",{"->":".^.s0","c":true},"ev","du",1,"==","/ev",{"->":".^.s1","c":true},"ev","du",2,"==","/ev",{"->":".^.s2","c":true},"nop",{"s0":["pop","^So, what are we gonna do about it? ",{"->":".^.^.23"},null],"s1":["pop","^ You're sorry for what? ",{"->":".^.^.23"},null],"s2":["pop",{"->":".^.^.23"},null],"#f":5}],"\n","ev","str","^I said I was sorry.","/str","/ev",{"*":".^.c-0","flg":20},"ev","str",["ev","visit",1,"MIN","/ev","ev","du",0,"==","/ev",{"->":".^.s0","c":true},"ev","du",1,"==","/ev",{"->":".^.s1","c":true},"nop",{"s0":["pop","^I'm sorry. ",{"->":".^.^.17"},null],"s1":["pop","^ For crashing my car behind your shop epic style.",{"->":".^.^.17"},null],"#f":5}],"/str","/ev",{"*":".^.c-1","flg":20},{"c-0":["\n","^You didn't, actually.","\n",["ev","str","^Yeah.","/str","/ev",{"*":".^.c-0","flg":20},{"c-0":["\n",{"->":"Intro.Apologize"},{"#f":5}]}],{"#f":5}],"c-1":["\n","^That wasn't so hard, now was it? Now get lost, I don't wanna see your face again.","\n","ev",true,"/ev",{"VAR=":"talkedToBossMan","re":true},"ev",{"VAR?":"finishedCrimeScene"},"/ev",[{"->":".^.b","c":true},{"b":["\n","^Actually... I kinda need to take your statement. I'm here on behalf of Peter. ","#","^speaker: Player","/#","\n","ev","str","^For fuck's sake.","/str","/ev",{"->":"StartQuestion"},{"->":".^.^.^.12"},null]}],[{"->":".^.b"},{"b":["\n","done",{"->":".^.^.^.12"},null]}],"nop","\n",{"#f":5}]}],{"#f":1}],"Apologize":[[["ev","visit",3,"%","/ev","ev","du",0,"==","/ev",{"->":".^.s0","c":true},"ev","du",1,"==","/ev",{"->":".^.s1","c":true},"ev","du",2,"==","/ev",{"->":".^.s2","c":true},"nop",{"s0":["pop","^You still haven't. ",{"->":".^.^.23"},null],"s1":["pop","^ Still waiting. ",{"->":".^.^.23"},null],"s2":["pop","^ What was that? ",{"->":".^.^.23"},null],"#f":5}],"\n","ev","str","^Ok, I'm sorry.","/str","/ev",{"*":".^.c-0","flg":20},"ev","str",["ev","visit",4,"%","/ev","ev","du",0,"==","/ev",{"->":".^.s0","c":true},"ev","du",1,"==","/ev",{"->":".^.s1","c":true},"ev","du",2,"==","/ev",{"->":".^.s2","c":true},"ev","du",3,"==","/ev",{"->":".^.s3","c":true},"nop",{"s0":["pop","^Cool. ",{"->":".^.^.29"},null],"s1":["pop","^ Right on. ",{"->":".^.^.29"},null],"s2":["pop","^ Yeah. ",{"->":".^.^.29"},null],"s3":["pop","^ You know...",{"->":".^.^.29"},null],"#f":5}],"/str","/ev",{"*":".^.c-1","flg":4},{"c-0":["\n",{"->":"Intro.IntroCont"},{"#f":5}],"c-1":["\n",{"->":".^.^.^"},{"#f":5}]}],{"#f":1}],"#f":1}],"CanQuestion":["ev",{"VAR?":"isTalkingToPolice"},"/ev",[{"->":".^.b","c":true},{"b":["^ ",{"->":"StartQuestion.TalkingToPolice"},{"->":".^.^.^.4"},null]}],"nop","\n","^What's going on, big guy? Crash any cars lately? ","#","^speaker: Boss Man ","/#","#","^anim: Talking","/#","\n","ev",{"VAR?":"finishedCrimeScene"},"/ev",[{"->":".^.b","c":true},{"b":["^ ",{"->":".^.^.^.Question"},{"->":".^.^.^.19"},null]}],[{"->":".^.b"},{"b":["^ I don't have time for this bozo, I've got a crime scene to investigate. ","end",{"->":".^.^.^.19"},null]}],"nop","\n",{"Question":[["ev","str","^I've got some questions for you.","/str","/ev",{"*":".^.c-0","flg":20},"ev","str","^I gots to go now, baby.","/str","/ev",{"*":".^.c-1","flg":20},{"c-0":["\n","ev","str","^What about?","/str","/ev",{"->":"StartQuestion"},{"#f":5}],"c-1":["\n","end",{"#f":5}]}],{"#f":1}],"#f":1}],"StartQuestion":[{"temp=":"msg"},["ev",true,"/ev",{"VAR=":"talkedToBossMan","re":true},"ev",{"VAR?":"msg"},"out","/ev","^ ","#","^speaker: Boss Man ","/#","#","^anim: Talking","/#","\n","ev",{"CNT?":".^.^.Call"},{"CNT?":".^.^.Relation"},"&&","/ev",[{"->":".^.b","c":true},{"b":["^ ",{"->":".^.^.^.^.DeadEnd"},{"->":".^.^.^.22"},null]}],"nop","\n","ev","str","^<b>Distract him</b>","/str",{"VAR?":"canDistract"},{"VAR?":"Clues"},{"VAR?":"victimWallet"},"!?","&&","/ev",{"*":".^.c-0","flg":21},"ev","str","^<color=#FFFF00>The victim came here last night.</color>","/str",{"VAR?":"knowledge"},{"VAR?":"receiptsBelongToVictim"},"?",{"VAR?":"Clues"},{"VAR?":"victimWallet"},"!?","&&","/ev",{"*":".^.c-1","flg":21},"ev","str","^<color=#FFFF00>About this wallet...</color>","/str",{"VAR?":"Clues"},{"VAR?":"victimWallet"},"?",{"VAR?":"knowledge"},{"VAR?":"stoleWallet"},"!?","&&","/ev",{"*":".^.c-2","flg":21},"ev","str","^<color=#FFFF00> Continue Interrogation</color>","/str",{"VAR?":"knowledge"},{"VAR?":"stoleWallet"},"?","/ev",{"*":".^.c-3","flg":21},"ev","str","^Did you make the call?","/str",{"VAR?":"canDistract"},"!",{"VAR?":"Suspects"},{"VAR?":"bossMan"},"!?","&&","/ev",{"*":".^.c-4","flg":21},"ev","str","^Did you know the victim?","/str",{"VAR?":"canDistract"},"!",{"VAR?":"Suspects"},{"VAR?":"bossMan"},"!?","&&","/ev",{"*":".^.c-5","flg":21},"ev","str","^Bye loser.","/str","/ev",{"*":".^.c-6","flg":20},{"c-0":["^ ",{"->":".^.^.^.Police"},"\n",{"#f":5}],"c-1":["^ ",{"->":".^.^.^.InquireAboutReceipt"},"\n",{"#f":5}],"c-2":["^ ",{"->":".^.^.^.Wallet"},"\n",{"#f":5}],"c-3":["^ ",{"->":".^.^.^.LastNight"},"\n",{"#f":5}],"c-4":["^ ",{"->":".^.^.^.Call"},"\n",{"#f":5}],"c-5":["^ ",{"->":".^.^.^.Relation"},"\n",{"#f":5}],"c-6":["^ ","end","\n",{"#f":5}]}],{"Police":["^The officer needs to take your statement. Again... ","#","^speaker: Player","/#","\n","^Are you kidding me? What more can I say that I haven't already told you people? How incompetent are you!? ","#","^speaker: Boss Man","/#","\n","^You don't really have much of a choice. He's expecting you by the scene, so if I were you I would get going. ","#","^speaker: Player","/#","\n","ev","str","^Walking","/str",{"x()":"startMovement","exArgs":1},"pop","/ev","\n","ev","str","^Boss Man","/str",{"x()":"focusCamera","exArgs":1},"pop","/ev","\n","^Unbelievable... This is what my skattepengar goes to. ","#","^speaker: Boss Man","/#","\n","^<i>Beautiful, he's left the shop unattended. Now I can have a little look around...</i> ","#","^speaker: Player","/#","\n","ev",{"x()":"resetCamera"},"pop","/ev","\n","ev",true,"/ev",{"VAR=":"isTalkingToPolice","re":true},"end",{"#f":1}],"TalkingToPolice":["^What is this? You told me that the officer had to take my statement. ","#","^speaker: Boss Man ","/#","#","^anim: Talking","/#","\n","^Yeah. What's the problem? ","#","^speaker: Player","/#","\n","ev","str","^Police Officer","/str",{"x()":"focusCamera","exArgs":1},"pop","/ev","\n","^Detective, I said that <b>you</b> were supposed to take his statement. ","#","^speaker: Police","/#","\n","^Oh. Sorry! Let me do that now real quick. ","#","^speaker: Player","/#","\n","ev","str","^Walking","/str",{"x()":"startMovement","exArgs":1},"pop","/ev","\n","ev","str","^Boss Man","/str",{"x()":"focusCamera","exArgs":1},"pop","/ev","\n","^You already took my statement! Fuck this. Don't waste my time again. ","#","^speaker: Boss Man","/#","\n","ev","str","^Police Officer","/str",{"x()":"focusCamera","exArgs":1},"pop","/ev","\n","^C'mon, detective. This is just embarassing. ","#","^speaker: Police","/#","\n","^You don't know the half of it. ","#","^speaker: Player","/#","\n","ev",{"x()":"resetCamera"},"pop","/ev","\n","ev",false,"/ev",{"VAR=":"isTalkingToPolice","re":true},"end",{"#f":1}],"InquireAboutReceipt":["^Huh? ","#","^speaker: Boss Man","/#","\n","^I have proof that he came here. I have a receipt from this shop that matches his card number. ","#","^speaker: Player ","/#","#","^portrait: 0","/#","\n","^Oh. Well, that's nothing. ","#","^speaker: Boss Man ","/#","#","^portrait:","/#","\n","^Huh? ","#","^speaker: Player","/#","\n","^Did you know he constantly lost his wallet? Someone must have found it and treated themself to one of my famous rolls. It's not the first time it's happened, or the last. ","#","^speaker: Boss Man","/#","\n","^Though, I guess this actually <b>would</b> be the last time... ","#","^anim: Shake","/#","\n","^I guess that makes sense... The officer told me he would lose it a lot. Even the bartender said so. ","#","^speaker: Player","/#","\n","^To weasel out of paying his tab, no doubt! ","#","^speaker: Boss Man","/#","\n","^Look, he didn't come here, alright? But I guess I could keep an eye out in case it shows up again.","\n","ev","str","^Anything else?","/str","/ev",{"->":".^.^"},"end",{"#f":1}],"DeadEnd":["^<i>He knows more than he lets on. Call it a hunch, but I've seen this type of guy before...</i> ","#","^speaker:","/#","\n","^<i>Som på Bollen i Rullen 25 på Nobeltorget.</i>","\n","^<i>Maybe he really doesn't know anything. Or I could take a little look around his shop... But I need to find a way to distract him somehow.</i>","\n","ev",true,"/ev",{"VAR=":"canDistract","re":true},"end",{"#f":1}],"AskAboutSuspects":[["ev","str","^About the bartender...","/str",{"VAR?":"Suspects"},{"VAR?":"bartender"},"?","/ev",{"*":".^.c-0","flg":21},"ev","str","^About the store clerk...","/str",{"VAR?":"Suspects"},{"VAR?":"storeClerk"},"?","/ev",{"*":".^.c-1","flg":21},{"c-0":["\n",{"->":".^.^.g-0"},{"#f":5}],"c-1":["\n",{"->":".^.^.g-0"},{"#f":5}],"g-0":["ev","str","^Här tar det stopp! Går tillbaka till hubben","/str","/ev",{"->":".^.^.^.^"},"ev","str","^Ask about something else","/str","/ev",{"*":".^.c-2","flg":20},{"c-2":["^ ","ev","str","^Hm.","/str","/ev",{"->":".^.^.^.^.^"},"\n",{"#f":5}],"#f":5}]}],{"#f":1}],"Relation":["^Sure, if being pestered by an alcoholic in nearly every aspect of my life counts as knowing him. ","#","^speaker: Boss Man","/#","\n","^I'd say that counts. ","#","^speaker: Player","/#","\n","^Alright, he wasn't all bad. He was a paying customer, which isn't something that most people would agree with me on. ","#","^speaker: Boss Man","/#","\n","^What do you mean? ","#","^speaker: Player","/#","\n","^He goes to the bar pretty much every day, drinking his life away. He's racked up a pretty sizeable tab I've heard, which won't ever get paid off at this point. ","#","^speaker: Boss Man","/#","\n","^The bartender is too good on him. Peter knew that shit wouldn't fly with me though, but the bartender needs all the business he can get. Even if that business is putting him deeper in debt.","\n","^I see. I'll make sure to talk to him as well, but right now I'm more interested in your relationship to the victim. ","#","^speaker: Player","/#","\n","^Sorry, I can't tell you anything that I haven't already said. ","<>","\n","ev","str","^Anything else?","/str","/ev",{"->":".^.^"},{"#f":1}],"Wallet":["^Did you steal that from my shop? ","#","^speaker: Boss Man ","/#","#","^anim: Angry","/#","\n","^It's not stealing if it's not yours, is it? ","#","^speaker: Player","/#","\n","^I don't like what you're implying. Look, I know it belonged to Peter. He would lose his wallet <i>constantly</i>. I find it, hold on to it, he comes back the next day and asks if I found it. Rinse and repeat. ","#","^speaker: Boss Man ","/#","#","^anim: Angry","/#","\n","^He would just expect me to have it, and we would keep having this little back and forth.","\n","^Only this time he never came back... ","#","^anim: Shake","/#","\n","^When did you find this wallet, exactly? ","#","^speaker: Player","/#","\n","^Let's see... I must have found it sometime before 2 A.M. He probably dropped it after he left the bar. ","#","^speaker: Boss Man","/#","\n","^And you're sure that he never came here at any point last night? ","#","^speaker: Player","/#","\n","^Like I said. Are we done here? ","#","^speaker: Boss Man","/#","\n","ev",{"VAR?":"knowledge"},{"VAR?":"receiptsBelongToVictim"},"?","/ev",[{"->":".^.b","c":true},{"b":["\n",{"->":".^.^.^.^.WalletCont"},{"->":".^.^.^.55"},null]}],[{"->":".^.b"},{"b":["\n","^<i>He's only telling half the truth. I can't press this issue further though, I have to find something more tangible and come back to this.</i> ","#","^speaker:","/#","\n","ev","str","^Anything else?","/str","/ev",{"->":".^.^.^.^"},{"->":".^.^.^.55"},null]}],"nop","\n","end",{"#f":1}],"WalletCont":["^<i>The receipts you found in the trash earlier contradict this statement. They clearly show that a purchase was made with his card after the time Boss Man supposedly found the wallet.</i> ","#","^portrait: 0","/#","\n","^That doesn't add up. Take a look at this receipt here. ","#","^portrait:","/#","\n","^You see Boss Man's eyes glance across the receipt, while he's trying to understand where you're going with this. ","#","^speaker:","/#","\n","^I'd recognize a receipt from my shop, obviously. What's the angle here? ","#","^speaker: Boss Man","/#","\n","^Well, guess who this receipt belonged to? ","#","^speaker: Player","/#","\n","^His eyes stop and dart up from the receipt to look back at you. ","#","^speaker:","/#","\n","^That's right bitch boy... It's clear as day that Peter was here last night, after 2 A.M and shortly before his estimated time of death, buying his nightly falafel. ","#","^speaker: Player","/#","\n","^Ok, wait a minute here, hold on... I just <i>forgot</i> he came here. It was a busy night, and I was tired, yeah? ","#","^speaker: Boss Man","/#","\n","^Bullshit artist. Even if that were true, that would mean he still had his wallet on him. And now it's here, with you instead... See where I'm going with this? ","#","^speaker: Player","/#","\n","ev",{"VAR?":"stoleWallet"},{"f()":"gainknowledge"},"pop","/ev","\n","^He came here last night, bought a falafel, and as he walked away, you went after. Killed him, took his wallet. Bam.","\n","^No, you're wrong! I didn't kill the poor guy! Let me explain...","\n","^What's there to explain? You have his wallet, the only way you could have it is if you took it from his body.","\n","^Like you took his wallet, I'm taking you... in, for murder.","\n","^No, wait! I <i>DID</i> take his wallet after I found his body, yeah? But I didn't <i>KILL HIM!</i>","\n",{"->":".^.^.LastNight"},{"#f":1}],"LastNight":["^It's true, I found his body and decided to take his wallet. I was just gonna grab some cash and then give it back to him like normal the next day. ","#","^speaker: Boss Man","/#","\n","^Just like I told you before, I soon realized that he was actually dead and so I called the cops.","\n","^Then I realized that I still had his wallet, which wasn't a good look for me. I couldn't admit something like that, that would make me look guilty! So I never mentioned it.","\n","^He died <i>shortly</i> after leaving your shop. You know how it looks, right? ","#","^speaker: Player","/#","\n","^I didn't do it, please believe me! ","#","^speaker: Boss Man","/#","\n","^Why should I? You lied to me before, you might still be lying.","\n","^You could have knocked him the fuck out, and it happened to kill him. Let's just say it was manslaughter and call it a day, huh? Heat of the moment! ","#","^speaker: Player","/#","\n","^I overheard you speaking with the Officer earlier, and he clearly stated that the victim couldn't have died from that! That means I couldn't have done it, yeah? ","#","^speaker: Boss Man","/#","\n","ev",{"VAR?":"knowledge"},{"VAR?":"victimPoisoned"},"?","/ev",[{"->":".^.b","c":true},{"b":["\n","^It's very likely that the victim was poisoned, and this falafelrulle right here <i>could</i> be the culprit. ","#","^portrait: 2 ","/#","#","^speaker: Player","/#","\n","^That's bullshit, <i>could</i> means that you don't have any real proof! ","#","^speaker: Boss Man","/#","\n","^Eat it. ","#","^speaker: Player","/#","\n","^Beat it. ","#","^speaker: Boss Man","/#","\n","^No, I mean <b>eat it</b>. This falafelrulle. If it's not poisoned, it should be fine to eat, right? ","#","^speaker: Player","/#","\n","^I'm... I'm not eating that. I don't know how old that thing is, and you could have put something in it yourself! ","#","^speaker: Boss Man","/#","\n","^And I no longer have any reason to trust you. I have everything I need here. ","#","^speaker: Player ","/#","#","^portrait:","/#","\n","^Wait! I have information! I can tell you about something Peter told me last night. ","#","^speaker: Boss Man","/#","\n","ev","str","^<b>Go on...<b>","/str","/ev",{"*":".^.c-0","flg":20},"ev","str","^<b>Not interested.</b>","/str","/ev",{"*":".^.c-1","flg":20},{"->":".^.^.^.38"},{"c-0":["\n",{"->":".^.^.^.^.^.StoreClerkFight"},{"#f":5}],"c-1":["\n","^Not interested. Like I said, I have everything I need here. ","#","^speaker: Player","/#","\n",{"->":".^.^.^.^.^.UnlockSuspect"},{"#f":5}]}]}],[{"->":".^.b"},{"b":["\n","^<i>I guess that makes sense. I don't think I have anything to prove an alternative theory.</i> ","#","^speaker:","/#","\n","^<i>Still, I know I'm onto something here... I'm just missing a small piece. I could ask around and see if I find out something interesting.</i>","\n","end",{"->":".^.^.^.38"},null]}],"nop","\n",{"#f":1}],"StoreClerkFight":["^Alright, let's hear it. ","#","^speaker: Player","/#","\n","^When he came here last night and bought his nightly falafelrulle, he told me that he and the cashier down by the gas station had an argument about something. ","#","^speaker: Boss Man","/#","\n","^So what? That doesn't mean anything. I can imagine that a lot of people had a bone to pick with Peter. ","#","^speaker: Player","/#","\n","^Yeah, yeah; but this was something else. He would always tell me whenever he got into trouble with the police, or if he was kicked out of the bar because of his shitty karaoke, and so on. ","#","^speaker: Boss Man","/#","\n","^But last night... He seemed off. When I asked him about what he and the cashier were arguing about, he got pissed and started yelling at me. So I didn't press him any further, and then he left. And you know the rest.","\n","^<i>I could choose to follow up on this lead, and even if it leads nowhere; I still have my prime suspect right here.</i> ","#","^speaker:","/#","\n","^Alright. I'll see where this goes, but don't expect to be in the clear because of this. ","#","^speaker: Player","/#","\n",{"->":".^.^.UnlockSuspect"},{"#f":1}],"UnlockSuspect":["ev",{"VAR?":"bossMan"},{"f()":"addsuspect"},"pop","/ev","\n","ev",{"VAR?":"bossManID"},{"x()":"unlockSuspect","exArgs":1},"pop","/ev","\n","^<i>You have unlocked Boss Man as a suspect. You can now speak with The Officer regarding this or consult your Field Manual for further information.</i> ","#","^speaker:","/#","\n","end",{"#f":1}],"Call":["^Didn't you already take my statement about this? ","#","^speaker: Boss Man","/#","\n","^The officer did, yes. I would like to hear it as well. Spare me no details, capische? ","#","^speaker: Player","/#","\n","^Fine, the quicker the better. ","#","^speaker: Boss Man","/#","\n","^Last night, at maybe around 2 A.M, I closed up shop and headed home.","\n","^That's when I stumbled upon him. I though for sure that he had just passed out from another night of drinking.","\n","^But... he wasn't breathing. I tried to wake him up, but I got no response.","\n","^I realized he wasn't just black out drunk, and quickly called the cops. They arrived almost immediately, I didn't even have time to...","\n","^...you know, do anything else. I mean, I didn't know what to do really.","\n","^He didn't come by here last night then? I was told he was a regular here, to a fault almost. ","#","^speaker: Player","/#","\n","ev","str","^No, he didn't. That's all I have to say about that.","/str","/ev",{"->":".^.^"},{"#f":1}],"#f":1}],"unlockAllSuspects":["ev",{"VAR?":"storeClerk"},{"f()":"addsuspect"},"pop","/ev","\n","ev",{"VAR?":"bossMan"},{"f()":"addsuspect"},"pop","/ev","\n","ev",{"VAR?":"bartender"},{"f()":"addsuspect"},"pop","/ev","\n","ev",{"VAR?":"storeClerkID"},{"x()":"unlockSuspect","exArgs":1},"pop","/ev","\n","ev",{"VAR?":"bossManID"},{"x()":"unlockSuspect","exArgs":1},"pop","/ev","\n","ev",{"VAR?":"bartenderID"},{"x()":"unlockSuspect","exArgs":1},"pop","/ev","\n",{"#f":1}],"addsuspect":[{"temp=":"x"},"ev",{"VAR?":"Suspects"},{"VAR?":"x"},"+",{"VAR=":"Suspects","re":true},"/ev",{"#f":1}],"getclue":[{"temp=":"x"},"ev",{"VAR?":"Clues"},{"VAR?":"x"},"+",{"VAR=":"Clues","re":true},"/ev",{"#f":1}],"gainknowledge":[{"temp=":"x"},"ev",{"VAR?":"knowledge"},{"VAR?":"x"},"+",{"VAR=":"knowledge","re":true},"/ev",{"#f":1}],"getitem":[{"temp=":"x"},"ev",{"VAR?":"items"},{"VAR?":"x"},"+",{"VAR=":"items","re":true},"/ev",{"#f":1}],"foundAllClues":["ev",{"VAR?":"cluesFoundonBody"},2,">=",{"VAR?":"cluesFoundbyBody"},1,">=","&&","/ev","~ret",{"#f":1}],"pop":[{"temp=":"list"},"ev",{"VAR?":"list"},"LIST_MIN","/ev",{"temp=":"x"},"\n","ev",{"VAR?":"list"},{"VAR?":"x"},"-",{"temp=":"list","re":true},"/ev","ev",{"VAR?":"x"},"/ev","~ret",{"#f":1}],"get":[{"temp=":"x"},"ev",{"VAR?":"Inventory"},{"VAR?":"x"},"+",{"VAR=":"Inventory","re":true},"/ev",{"#f":1}],"move_to_supporter":[{"temp=":"new_supporter"},{"temp=":"item_state"},"ev",{"VAR?":"item_state"},{"VAR?":"Supporters"},"LIST_ALL","-",{"temp=":"item_state","re":true},"/ev","\n","ev",{"VAR?":"item_state"},{"VAR?":"new_supporter"},"+",{"temp=":"item_state","re":true},"/ev",{"#f":1}],"reached":[{"temp=":"x"},"ev",{"VAR?":"knowledgeState"},{"VAR?":"x"},"?","/ev","~ret",{"#f":1}],"between":[{"temp=":"y"},{"temp=":"x"},"ev",{"VAR?":"knowledgeState"},{"VAR?":"x"},"?",{"VAR?":"knowledgeState"},{"VAR?":"y"},"L^","!","&&","/ev","~ret",{"#f":1}],"reach":[{"temp=":"statesToSet"},"ev",{"^var":"statesToSet","ci":-1},{"f()":"pop"},"/ev",{"temp=":"x"},"\n",["ev",{"VAR?":"x"},"!","/ev",{"->":".^.b","c":true},{"b":["\n","ev",false,"/ev","~ret",{"->":"reach.10"},null]}],["ev",{"VAR?":"x"},{"f()":"reached"},"!","/ev",{"->":".^.b","c":true},{"b":["\n","ev",{"VAR?":"x"},"LIST_ALL","/ev",{"temp=":"chain"},"\n","ev",{"VAR?":"chain"},{"VAR?":"chain"},"LIST_MIN",{"VAR?":"x"},"range","/ev",{"temp=":"statesGained"},"\n","ev",{"VAR?":"knowledgeState"},{"VAR?":"statesGained"},"+",{"VAR=":"knowledgeState","re":true},"/ev","ev",{"VAR?":"statesToSet"},{"f()":"reach"},"pop","/ev","\n","ev",true,"/ev","~ret",{"->":"reach.10"},null]}],[{"->":".^.b"},{"b":["\n","ev",false,{"VAR?":"statesToSet"},{"f()":"reach"},"||","/ev","~ret","\n",{"->":"reach.10"},null]}],"nop","\n",{"#f":1}],"murder_scene":[["^The bedroom. This is where it happened. Now to look for clues.","\n",["ev",{"VAR?":"bedroomLightState"},{"VAR?":"seen"},"?","/ev",[{"->":".^.b","c":true},{"b":["^ ","thread",{"->":".^.^.^.^.^.seen_light"},{"->":".^.^.^.6"},null]}],"nop","\n","ev",{"^->":"murder_scene.0.top"},"/ev","thread",{"->":".^.^.^.compare_prints"},"ev","str","^The bed...","/str","/ev",{"*":".^.c-0","flg":20},"ev","str","^ Look under the bed ","/str",{"CNT?":".^.c-0.9.bedhub.c-5"},{"VAR?":"bedroomLightState"},{"VAR?":"on_floor"},"?","&&",{"VAR?":"bedroomLightState"},{"VAR?":"on"},"?","&&","/ev",{"*":".^.c-1","flg":21},"ev","str","^Use the cane to reach under the bed ","/str",{"CNT?":".^.c-1.3.reaching"},{"^->":"murder_scene.0.top.c-1.3.reaching"},"turns",4,">=","&&",{"VAR?":"Inventory"},{"VAR?":"cane"},"?","&&","/ev",{"*":".^.c-2","flg":21},"ev","str","^Pick up the knife","/str",{"VAR?":"knifeState"},{"VAR?":"on_floor"},"?","/ev",{"*":".^.c-3","flg":21},"ev","str","^Look at the knife","/str",{"VAR?":"Inventory"},{"VAR?":"knife"},"?","/ev",{"*":".^.c-4","flg":21},"ev","str","^   The desk... ","/str","/ev",{"*":".^.c-5","flg":20},"ev","str","^Swoosh the cane","/str",{"VAR?":"Inventory"},{"VAR?":"cane"},"?",{"^->":"murder_scene.0.top.c-5.11.deskstate"},"turns",2,"<=","&&","/ev",{"*":".^.c-6","flg":21},"ev","str","^The window...","/str","/ev",{"*":".^.c-7","flg":20},"ev","str","^Leave the room","/str",{"CNT?":".^"},5,">=","/ev",{"*":".^.c-8","flg":21},{"c-0":["\n","^The bed was low to the ground, but not so low something might not roll underneath. It was still neatly made.","\n","ev",{"VAR?":"neatly_made"},{"f()":"reach"},"pop","/ev","\n",[["ev","str","^Lift the bedcover","/str","/ev",{"*":".^.c-0","flg":20},"ev","str","^Remove the cover","/str",{"VAR?":"crumpled_duvet"},{"f()":"reached"},"/ev",{"*":".^.c-1","flg":21},"ev","str","^ Pull back the duvet ","/str",{"VAR?":"BedState"},{"VAR?":"covers_off"},"==","/ev",{"*":".^.c-2","flg":21},"ev","str","^ Remake the bed ","/str",{"VAR?":"BedState"},{"VAR?":"made_up"},"!?","/ev",{"*":".^.c-3","flg":21},"ev","str","^Test the bed","/str","/ev",{"*":".^.c-4","flg":20},"ev","str","^Look under the bed","/str","/ev",{"*":".^.c-5","flg":20},"ev","str","^Something else?","/str",{"^->":"murder_scene.0.top.c-0"},"turns",1,">","/ev",{"*":".^.c-6","flg":21},{"c-0":["\n","^I lifted back the bedcover. The duvet underneath was crumpled.","\n","ev",{"VAR?":"crumpled_duvet"},{"f()":"reach"},"pop","/ev","\n","ev",{"VAR?":"covers_shifted"},"/ev",{"VAR=":"BedState","re":true},{"->":".^.^.^.g-0"},{"#f":5}],"c-1":["\n","^Careful not to disturb anything beneath, I removed the cover entirely. The duvet below was rumpled.","\n","^Not the work of the maid, who was conscientious to a point. Clearly this had been thrown on in a hurry.","\n","ev",{"VAR?":"hastily_remade"},{"f()":"reach"},"pop","/ev","\n","ev",{"VAR?":"covers_off"},"/ev",{"VAR=":"BedState","re":true},{"->":".^.^.^.g-0"},{"#f":5}],"c-2":["\n","^I pulled back the duvet. Beneath it was a sheet, sticky with blood.","\n","ev",{"VAR?":"bloodstain_visible"},"/ev",{"VAR=":"BedState","re":true},"ev",{"VAR?":"body_on_bed"},{"f()":"reach"},"pop","/ev","\n","^Either the body had been moved here before being dragged to the floor - or this is was where the murder had taken place.","\n",{"->":".^.^.^.g-0"},{"#f":5}],"c-3":["\n","^Carefully, I pulled the bedsheets back into place, trying to make it seem undisturbed.","\n","ev",{"VAR?":"made_up"},"/ev",{"VAR=":"BedState","re":true},{"->":".^.^.^.g-0"},{"#f":5}],"c-4":["\n","^I pushed the bed with spread fingers. It creaked a little, but not so much as to be obnoxious.","\n",{"->":".^.^.^.g-0"},{"#f":5}],"c-5":["\n","^Lying down, I peered under the bed, but could make nothing out.","\n",{"->":".^.^.^.g-0"},{"#f":5}],"c-6":["\n","^I took a step back from the bed and looked around.","\n",{"->":".^.^.^.^.^"},{"->":".^.^.^.g-0"},{"#f":5}],"#f":5,"#n":"bedhub"}],{"g-0":[{"->":".^.^.bedhub"},{"->":".^.^.^.^.^.g-0"},{"#f":5}]}],{"#f":7}],"c-1":["\n","^I peered under the bed. Something glinted back at me.","\n",[["ev","str","^ Reach for it ","/str","/ev",{"*":".^.c-0","flg":20},"ev","str","^Knock it with the cane","/str",{"VAR?":"Inventory"},{"VAR?":"cane"},"?","/ev",{"*":".^.c-1","flg":21},"ev","str","^ Stand up ","/str",{"CNT?":".^"},1,">","/ev",{"*":".^.c-2","flg":21},{"c-0":["\n","^I fished with one arm under the bed, but whatever it was, it had been kicked far enough back that I couldn't get my fingers on it.","\n",{"->":".^.^"},{"->":".^.^.^.^.^.^.g-0"},{"#f":5}],"c-1":["\n",{"->":".^.^.^.^.^.c-2"},{"->":".^.^.^.^.^.^.g-0"},{"#f":5}],"c-2":["\n","^I stood up once more, and brushed my coat down.","\n",{"->":".^.^.^.^.^"},{"->":".^.^.^.^.^.^.g-0"},{"#f":5}],"#f":7,"#n":"reaching"}],null],{"#f":5}],"c-2":["\n","^Positioning the cane above the carpet, I gave the glinting thing a sharp tap. It slid out from the under the foot of the bed.","\n","ev",{"^var":"knifeState","ci":-1},{"VAR?":"on_floor"},{"f()":"move_to_supporter"},"pop","/ev","\n",["ev","str","^Stand up","/str","/ev",{"*":".^.c-0","flg":20},"ev","str","^Look under the bed once more","/str","/ev",{"*":".^.c-1","flg":20},{"c-0":["\n","^Satisfied, I stood up, and saw I had knocked free a bloodied knife.","\n",{"->":".^.^.^.^"},{"->":".^.^.^.^.^.g-0"},{"#f":5}],"c-1":["\n","^Moving the cane aside, I looked under the bed once more, but there was nothing more there.","\n",{"->":".^.^.c-0"},{"->":".^.^.^.^.^.g-0"},{"#f":5}]}],{"#f":5}],"c-3":["\n","^Careful not to touch the handle, I lifted the blade from the carpet.","\n","ev",{"VAR?":"knife"},{"f()":"get"},"pop","/ev","\n",{"->":".^.^.^.g-0"},{"#f":5}],"c-4":["\n","^The blood was dry enough. Dry enough to show up partial prints on the hilt!","\n","ev",{"VAR?":"prints_on_knife"},{"f()":"reach"},"pop","/ev","\n",{"->":".^.^.^.g-0"},{"#f":5}],"c-5":["\n","^I turned my attention to the desk. A lamp sat in one corner, a neat, empty in-tray in the other. There was nothing else out.","\n","^Leaning against the desk was a wooden cane.","\n","ev",{"VAR?":"bedroomLightState"},{"VAR?":"seen"},"+",{"VAR=":"bedroomLightState","re":true},"/ev",[["ev","str","^Pick up the cane ","/str",{"VAR?":"Inventory"},{"VAR?":"cane"},"!?","/ev",{"*":".^.c-0","flg":21},"ev","str","^Turn on the lamp","/str",{"VAR?":"bedroomLightState"},{"VAR?":"on"},"!?","/ev",{"*":".^.c-1","flg":21},"ev","str","^Look at the in-tray ","/str","/ev",{"*":".^.c-2","flg":20},"ev","str","^Open a drawer","/str",{"CNT?":".^.c-3"},3,"<","/ev",{"*":".^.c-3","flg":5},"ev","str","^Something else?","/str",{"CNT?":".^"},2,">=","/ev",{"*":".^.c-4","flg":21},{"c-0":["\n","ev",{"VAR?":"cane"},{"f()":"get"},"pop","/ev","\n","^I picked up the wooden cane. It was heavy, and unmarked.","\n",{"->":".^.^.^.g-0"},{"#f":5}],"c-1":["\n",{"->t->":"murder_scene.operate_lamp"},{"->":".^.^.^.g-0"},{"#f":5}],"c-2":["\n","^I regarded the in-tray, but there was nothing to be seen. Either the victim's papers were taken, or his line of work had seriously dried up. Or the in-tray was all for show.","\n",{"->":".^.^.^.g-0"},{"#f":5}],"c-3":["\n","^I tried ",["ev","visit",2,"MIN","/ev","ev","du",0,"==","/ev",{"->":".^.s0","c":true},"ev","du",1,"==","/ev",{"->":".^.s1","c":true},"ev","du",2,"==","/ev",{"->":".^.s2","c":true},"nop",{"s0":["pop","^a drawer at random",{"->":".^.^.23"},null],"s1":["pop","^another drawer",{"->":".^.^.23"},null],"s2":["pop","^a third drawer",{"->":".^.^.23"},null],"#f":5}],"^. ",["ev","visit",2,"MIN","/ev","ev","du",0,"==","/ev",{"->":".^.s0","c":true},"ev","du",1,"==","/ev",{"->":".^.s1","c":true},"ev","du",2,"==","/ev",{"->":".^.s2","c":true},"nop",{"s0":["pop","^Locked",{"->":".^.^.23"},null],"s1":["pop","^Also locked",{"->":".^.^.23"},null],"s2":["pop","^Unsurprisingly, locked as well",{"->":".^.^.23"},null],"#f":5}],"^.","\n",{"->":".^.^.^.g-0"},{"#f":5}],"c-4":["\n","^I took a step away from the desk once more.","\n",{"->":".^.^.^.^.^"},{"->":".^.^.^.g-0"},{"#f":5}],"#f":7,"#n":"deskstate"}],{"g-0":[{"->":".^.^.deskstate"},{"->":".^.^.^.^.^.g-0"},{"#f":5}]}],{"#f":5}],"c-6":["\n","^I was still holding the cane: I gave it an experimental swoosh. It was heavy indeed, though not heavy enough to be used as a bludgeon.","\n","^But it might have been useful in self-defence. Why hadn't the victim reached for it? Knocked it over?","\n",{"->":".^.^.^.g-0"},{"#f":5}],"c-7":["\n","^I went over to the window and peered out. A dismal view of the little brook that ran down beside the house.","\n",[["ev",{"^->":"murder_scene.0.top.c-7.3.window_opts"},"/ev","thread",{"->":"murder_scene.compare_prints"},"ev","str","^Look down at the brook","/str","/ev",{"*":".^.c-0","flg":20},"ev","str","^Look at the glass","/str","/ev",{"*":".^.c-1","flg":20},"ev","str","^ Look at the steam ","/str",{"VAR?":"GlassState"},{"VAR?":"steamed"},"?",{"CNT?":"murder_scene.see_prints_on_glass"},"!","&&",{"CNT?":".^.c-0"},"&&",{"CNT?":".^.c-1"},"&&","/ev",{"*":".^.c-2","flg":21},"ev","str","^ Breathe on the glass ","/str",{"VAR?":"GlassState"},{"VAR?":"steam_gone"},"?","/ev",{"*":".^.c-3","flg":5},"ev","str","^Something else?","/str","/ev",{"*":".^.c-4","flg":4},{"c-0":["\n","ev",{"VAR?":"GlassState"},{"VAR?":"steamed"},"?","/ev",[{"->":".^.b","c":true},{"b":["\n","^Through the steamed glass I couldn't see the brook. ",{"->t->":"murder_scene.see_prints_on_glass"},{"->":".^.^.^.^"},"\n",{"->":".^.^.^.7"},null]}],"nop","\n","^I watched the little stream rush past for a while. The house probably had damp but otherwise, it told me nothing.","\n",{"->":".^.^.^.g-0"},{"#f":5}],"c-1":["\n","ev",{"VAR?":"GlassState"},{"VAR?":"steamed"},"?","/ev",[{"->":".^.b","c":true},{"b":["^ ",{"->":".^.^.^.^.c-0"},{"->":".^.^.^.7"},null]}],"nop","\n","^The glass in the window was greasy. No one had cleaned it in a while, inside or out.","\n",{"->":".^.^.^.g-0"},{"#f":5}],"c-2":["\n","^A cold day outside. Natural my breath should steam. ",{"->t->":"murder_scene.see_prints_on_glass"},"\n",{"->":".^.^.^.g-0"},{"#f":5}],"c-3":["\n","^I breathed gently on the glass once more. ","ev",{"VAR?":"fingerprints_on_glass"},{"f()":"reached"},"/ev",[{"->":".^.b","c":true},{"b":["^ The fingerprints reappeared. ",{"->":".^.^.^.7"},null]}],"nop","\n","ev",{"VAR?":"steamed"},"/ev",{"VAR=":"GlassState","re":true},{"->":".^.^.^.g-0"},{"#f":5}],"c-4":["\n","ev",{"CNT?":".^.^"},2,"<",{"VAR?":"fingerprints_on_glass"},{"f()":"reached"},"||",{"VAR?":"GlassState"},{"VAR?":"steamed"},"?","||","/ev",[{"->":".^.b","c":true},{"b":["\n","^I looked away from the dreary glass.","\n","ev",{"VAR?":"GlassState"},{"VAR?":"steamed"},"?","/ev",[{"->":".^.b","c":true},{"b":["\n","ev",{"VAR?":"steam_gone"},"/ev",{"VAR=":"GlassState","re":true},"<>","^ The steam from my breath faded.","\n",{"->":".^.^.^.9"},null]}],"nop","\n",{"->":".^.^.^.^.^.^.^"},{"->":".^.^.^.14"},null]}],"nop","\n","^I leant back from the glass. My breath had steamed up the pane a little.","\n","ev",{"VAR?":"steamed"},"/ev",{"VAR=":"GlassState","re":true},{"->":".^.^.^.g-0"},{"#f":5}],"#f":7,"#n":"window_opts"}],{"g-0":[{"->":".^.^.window_opts"},{"->":".^.^.^.^.^.g-0"},{"#f":5}]}],{"#f":5}],"c-8":["\n","^I'd seen enough. I ","ev",{"VAR?":"bedroomLightState"},{"VAR?":"on"},"?","/ev",[{"->":".^.b","c":true},{"b":["^switched off the lamp, then",{"->":".^.^.^.8"},null]}],"nop","^ turned and left the room.","\n",{"->":"joe_in_hall"},{"->":".^.^.^.g-0"},{"#f":5}],"#f":7,"#n":"top"}],{"g-0":[{"->":".^.^.top"},{"#f":5}]}],{"operate_lamp":["^I flicked the light switch.","\n","ev",{"VAR?":"bedroomLightState"},{"VAR?":"on"},"?","/ev",[{"->":".^.b","c":true},{"b":["\n","<>","^ The bulb fell dark.","\n","ev",{"VAR?":"bedroomLightState"},{"VAR?":"off"},"+",{"VAR=":"bedroomLightState","re":true},"/ev","ev",{"VAR?":"bedroomLightState"},{"VAR?":"on"},"-",{"VAR=":"bedroomLightState","re":true},"/ev",{"->":".^.^.^.9"},null]}],[{"->":".^.b"},{"b":["\n","ev",{"VAR?":"bedroomLightState"},{"VAR?":"on_floor"},"?","/ev",[{"->":".^.b","c":true},{"b":["^ ","<>","^ A little light spilled under the bed.",{"->":".^.^.^.7"},null]}],"nop","^ ","ev",{"VAR?":"bedroomLightState"},{"VAR?":"on_desk"},"?","/ev",[{"->":".^.b","c":true},{"b":["^ ","<>","^ The light gleamed on the polished tabletop. ",{"->":".^.^.^.15"},null]}],"nop","\n","ev",{"VAR?":"bedroomLightState"},{"VAR?":"off"},"-",{"VAR=":"bedroomLightState","re":true},"/ev","ev",{"VAR?":"bedroomLightState"},{"VAR?":"on"},"+",{"VAR=":"bedroomLightState","re":true},"/ev",{"->":".^.^.^.9"},null]}],"nop","\n","ev","void","/ev","->->",{"#f":1}],"compare_prints":[{"temp=":"backto"},["ev","str","^Compare the prints on the knife and the window ","/str",{"list":{"WindowKnowledge.fingerprints_on_glass":2,"KnifeKnowledge.prints_on_knife":1}},{"VAR?":"fingerprints_on_glass_match_knife"},{"f()":"between"},"/ev",{"*":".^.c-0","flg":21},{"c-0":["\n","^Holding the bloodied knife near the window, I breathed to bring out the prints once more, and compared them as best I could.","\n","^Hardly scientific, but they seemed very similar - very similiar indeed.","\n","ev",{"VAR?":"fingerprints_on_glass_match_knife"},{"f()":"reach"},"pop","/ev","\n",{"->":"backto","var":true},{"#f":5}]}],{"#f":1}],"see_prints_on_glass":["ev",{"VAR?":"fingerprints_on_glass"},{"f()":"reach"},"pop","/ev","\n",["ev","visit",1,"MIN","/ev","ev","du",0,"==","/ev",{"->":".^.s0","c":true},"ev","du",1,"==","/ev",{"->":".^.s1","c":true},"nop",{"s0":["pop","^But I could see a few fingerprints, as though someone hadpressed their palm against it.",{"->":".^.^.17"},null],"s1":["pop","^The fingerprints were quite clear and well-formed.",{"->":".^.^.17"},null],"#f":5}],"^ They faded as I watched.","\n","ev",{"VAR?":"steam_gone"},"/ev",{"VAR=":"GlassState","re":true},"ev","void","/ev","->->",{"#f":1}],"seen_light":[["ev","str","^ Turn on lamp ","/str",{"VAR?":"bedroomLightState"},{"VAR?":"on"},"!?","/ev",{"*":".^.c-0","flg":21},"ev","str","^ Move the light to the bed ","/str",{"VAR?":"bedroomLightState"},{"VAR?":"on_bed"},"!?",{"VAR?":"BedState"},{"VAR?":"bloodstain_visible"},"?","&&","/ev",{"*":".^.c-1","flg":21},"ev","str","^ Move the light back to the desk ","/str",{"VAR?":"bedroomLightState"},{"VAR?":"on_desk"},"!?",{"^->":"murder_scene.seen_light.0.c-3"},"turns",2,">=","&&","/ev",{"*":".^.c-2","flg":21},"ev","str","^Move the light to the floor ","/str",{"VAR?":"bedroomLightState"},{"VAR?":"on_floor"},"!?",{"CNT?":".^.^.^.0.top.c-0.9.bedhub.c-5"},"&&","/ev",{"*":".^.c-3","flg":21},{"c-0":["\n",{"->t->":".^.^.^.^.operate_lamp"},{"->":".^.^.g-0"},{"#f":5}],"c-1":["\n","ev",{"^var":"bedroomLightState","ci":-1},{"VAR?":"on_bed"},{"f()":"move_to_supporter"},"pop","/ev","\n","^I moved the light over to the bloodstain and peered closely at it. It had soaked deeply into the fibres of the cotton sheet.","\n","^There was no doubt about it. This was where the blow had been struck.","\n","ev",{"VAR?":"murdered_in_bed"},{"f()":"reach"},"pop","/ev","\n",{"->":".^.^.g-0"},{"#f":5}],"c-2":["\n","ev",{"^var":"bedroomLightState","ci":-1},{"VAR?":"on_desk"},{"f()":"move_to_supporter"},"pop","/ev","\n","^I moved the light back to the desk, setting it down where it had originally been.","\n",{"->":".^.^.g-0"},{"#f":5}],"c-3":["\n","ev",{"^var":"bedroomLightState","ci":-1},{"VAR?":"on_floor"},{"f()":"move_to_supporter"},"pop","/ev","\n","^I picked the light up and set it down on the floor.","\n",{"->":".^.^.g-0"},{"#f":7}],"g-0":[{"->":".^.^.^.^.0.top"},{"#f":5}]}],{"#f":1}],"#f":1}],"joe_in_hall":[["^My police contact, Joe, was waiting in the hall. 'So?' he demanded. 'Did you find anything interesting?'","\n",[["ev",{"^->":"joe_in_hall.0.found.0.$r1"},{"temp=":"$r"},"str",{"->":".^.s"},[{"#n":"$r1"}],"/str",{"CNT?":".^.^"},1,"==","/ev",{"*":".^.^.c-0","flg":19},{"s":["^'Nothing.'",{"->":"$r","var":true},null]}],["ev",{"^->":"joe_in_hall.0.found.1.$r1"},{"temp=":"$r"},"str",{"->":".^.s"},[{"#n":"$r1"}],"/str",{"VAR?":"Inventory"},{"VAR?":"knife"},"?","/ev",{"*":".^.^.c-1","flg":19},{"s":["^'I found the murder weapon.'",{"->":"$r","var":true},null]}],["ev",{"^->":"joe_in_hall.0.found.2.$r1"},{"temp=":"$r"},"str",{"->":".^.s"},[{"#n":"$r1"}],"/str","str","^.'","/str",{"VAR?":"prints_on_knife"},{"f()":"reached"},{"VAR?":"knifeState"},{"VAR?":"with_joe"},"?","&&","/ev",{"*":".^.^.c-2","flg":23},{"s":["^'There are prints on the blade",{"->":"$r","var":true},null]}],["ev",{"^->":"joe_in_hall.0.found.3.$r1"},{"temp=":"$r"},"str",{"->":".^.s"},[{"#n":"$r1"}],"/str",{"list":{"WindowKnowledge.fingerprints_on_glass_match_knife":3,"KnifeKnowledge.joe_seen_prints_on_knife":2}},{"f()":"reached"},"/ev",{"*":".^.^.c-3","flg":19},{"s":["^'They match a set of prints on the window, too.'",{"->":"$r","var":true},null]}],["ev",{"^->":"joe_in_hall.0.found.4.$r1"},{"temp=":"$r"},"str",{"->":".^.s"},[{"#n":"$r1"}],"/str","str","^.'","/str",{"VAR?":"body_on_bed"},{"VAR?":"murdered_in_bed"},{"f()":"between"},"/ev",{"*":".^.^.c-4","flg":23},{"s":["^'The body was moved to the bed at some point",{"->":"$r","var":true},null]}],["ev",{"^->":"joe_in_hall.0.found.5.$r1"},{"temp=":"$r"},"str",{"->":".^.s"},[{"#n":"$r1"}],"/str",{"VAR?":"murdered_in_bed"},{"f()":"reached"},"/ev",{"*":".^.^.c-5","flg":19},{"s":["^'The victim was murdered in bed, and then the body was moved to the floor.'",{"->":"$r","var":true},null]}],["ev",{"^->":"joe_in_hall.0.found.6.$r1"},{"temp=":"$r"},"str",{"->":".^.s"},[{"#n":"$r1"}],"/str",{"CNT?":".^.^"},1,">","/ev",{"*":".^.^.c-6","flg":19},{"s":["^'That's it.'",{"->":"$r","var":true},null]}],{"c-0":["ev",{"^->":"joe_in_hall.0.found.c-0.$r2"},"/ev",{"temp=":"$r"},{"->":".^.^.0.s"},[{"#n":"$r2"}],"\n","^He shrugged. 'Shame.'","\n",{"->":".^.^.^.g-0.done"},{"->":".^.^.^.g-0"},{"#f":5}],"c-1":["ev",{"^->":"joe_in_hall.0.found.c-1.$r2"},"/ev",{"temp=":"$r"},{"->":".^.^.1.s"},[{"#n":"$r2"}],"\n","^'Good going!' Joe replied with a grin. 'We thought the murderer had gotten rid of it. I'll bag that for you now.'","\n","ev",{"^var":"knifeState","ci":-1},{"VAR?":"with_joe"},{"f()":"move_to_supporter"},"pop","/ev","\n",{"->":".^.^.^.g-0"},{"#f":5}],"c-2":["ev",{"^->":"joe_in_hall.0.found.c-2.$r2"},"/ev",{"temp=":"$r"},{"->":".^.^.2.s"},[{"#n":"$r2"}],"^,' I told him.","\n","^He regarded them carefully.","\n","^'Hrm. Not very complete. It'll be hard to get a match from these.'","\n","ev",{"VAR?":"joe_seen_prints_on_knife"},{"f()":"reach"},"pop","/ev","\n",{"->":".^.^.^.g-0"},{"#f":5}],"c-3":["ev",{"^->":"joe_in_hall.0.found.c-3.$r2"},"/ev",{"temp=":"$r"},{"->":".^.^.3.s"},[{"#n":"$r2"}],"\n","^'Anyone could have touched the window,' Joe replied thoughtfully. 'But if they're more complete, they should help us get a decent match!'","\n","ev",{"VAR?":"joe_wants_better_prints"},{"f()":"reach"},"pop","/ev","\n",{"->":".^.^.^.g-0"},{"#f":5}],"c-4":["ev",{"^->":"joe_in_hall.0.found.c-4.$r2"},"/ev",{"temp=":"$r"},{"->":".^.^.4.s"},[{"#n":"$r2"}],"^,' I told him. 'And then moved back to the floor.'","\n","^'Why?'","\n",[["ev",{"^->":"joe_in_hall.0.found.c-4.10.0.$r1"},{"temp=":"$r"},"str",{"->":".^.s"},[{"#n":"$r1"}],"/str","/ev",{"*":".^.^.c-0","flg":18},{"s":["^'I don't know.'",{"->":"$r","var":true},null]}],["ev",{"^->":"joe_in_hall.0.found.c-4.10.1.$r1"},{"temp=":"$r"},"str",{"->":".^.s"},[{"#n":"$r1"}],"/str","/ev",{"*":".^.^.c-1","flg":18},{"s":["^'Perhaps to get something from the floor?'",{"->":"$r","var":true},null]}],["ev",{"^->":"joe_in_hall.0.found.c-4.10.2.$r1"},{"temp=":"$r"},"str",{"->":".^.s"},[{"#n":"$r1"}],"/str","/ev",{"*":".^.^.c-2","flg":18},{"s":["^'Perhaps he was killed in bed.'",{"->":"$r","var":true},null]}],{"c-0":["ev",{"^->":"joe_in_hall.0.found.c-4.10.c-0.$r2"},"/ev",{"temp=":"$r"},{"->":".^.^.0.s"},[{"#n":"$r2"}],"\n","^Joe nods. 'All right.'","\n",{"->":".^.^.^.^.^.g-0"},{"#f":5}],"c-1":["ev",{"^->":"joe_in_hall.0.found.c-4.10.c-1.$r2"},"/ev",{"temp=":"$r"},{"->":".^.^.1.s"},[{"#n":"$r2"}],"\n","^'You wouldn't move a whole body for that.'","\n",{"->":".^.^.^.^.^.g-0"},{"#f":5}],"c-2":["ev",{"^->":"joe_in_hall.0.found.c-4.10.c-2.$r2"},"/ev",{"temp=":"$r"},{"->":".^.^.2.s"},[{"#n":"$r2"}],"\n","^'It's just speculation at this point,' Joe remarks.","\n",{"->":".^.^.^.^.^.g-0"},{"#f":5}]}],{"#f":5}],"c-5":["ev",{"^->":"joe_in_hall.0.found.c-5.$r2"},"/ev",{"temp=":"$r"},{"->":".^.^.5.s"},[{"#n":"$r2"}],"\n","^'Why?'","\n",[["ev",{"^->":"joe_in_hall.0.found.c-5.9.0.$r1"},{"temp=":"$r"},"str",{"->":".^.s"},[{"#n":"$r1"}],"/str","/ev",{"*":".^.^.c-0","flg":18},{"s":["^'I don't know.'",{"->":"$r","var":true},null]}],["ev",{"^->":"joe_in_hall.0.found.c-5.9.1.$r1"},{"temp=":"$r"},"str",{"->":".^.s"},[{"#n":"$r1"}],"/str","/ev",{"*":".^.^.c-1","flg":18},{"s":["^'Perhaps the murderer wanted to mislead us.'",{"->":"$r","var":true},null]}],["ev",{"^->":"joe_in_hall.0.found.c-5.9.2.$r1"},{"temp=":"$r"},"str",{"->":".^.s"},[{"#n":"$r1"}],"/str","/ev",{"*":".^.^.c-2","flg":18},{"s":["^'Perhaps the murderer hoped to clean up the scene.'",{"->":"$r","var":true},null]}],{"c-0":["ev",{"^->":"joe_in_hall.0.found.c-5.9.c-0.$r2"},"/ev",{"temp=":"$r"},{"->":".^.^.0.s"},[{"#n":"$r2"}],"\n","^Joe nods. 'All right, then.'","\n",{"->":".^.^.^.^.^.g-0"},{"#f":5}],"c-1":["ev",{"^->":"joe_in_hall.0.found.c-5.9.c-1.$r2"},"/ev",{"temp=":"$r"},{"->":".^.^.1.s"},[{"#n":"$r2"}],"\n","^'How so?'","\n",[["ev",{"^->":"joe_in_hall.0.found.c-5.9.c-1.9.0.$r1"},{"temp=":"$r"},"str",{"->":".^.s"},[{"#n":"$r1"}],"/str","str","^.'","/str","/ev",{"*":".^.^.c-0","flg":22},{"s":["^'They wanted us to think the victim was awake",{"->":"$r","var":true},null]}],["ev",{"^->":"joe_in_hall.0.found.c-5.9.c-1.9.1.$r1"},{"temp=":"$r"},"str",{"->":".^.s"},[{"#n":"$r1"}],"/str","str","^.'","/str","/ev",{"*":".^.^.c-1","flg":22},{"s":["^'They wanted us to think there was some kind of struggle",{"->":"$r","var":true},null]}],{"c-0":["ev",{"^->":"joe_in_hall.0.found.c-5.9.c-1.9.c-0.$r2"},"/ev",{"temp=":"$r"},{"->":".^.^.0.s"},[{"#n":"$r2"}],"^, I replied thoughtfully. 'That they were meeting their attacker, rather than being stabbed in their sleep.'","\n",{"->":".^.^.g-0"},{"#f":5}],"c-1":["ev",{"^->":"joe_in_hall.0.found.c-5.9.c-1.9.c-1.$r2"},"/ev",{"temp=":"$r"},{"->":".^.^.1.s"},[{"#n":"$r2"}],"^,' I replied. 'That the victim wasn't simply stabbed in their sleep.'","\n",{"->":".^.^.g-0"},{"#f":5}],"g-0":["^'But if they were killed in bed, that's most likely what happened. Stabbed, while sleeping.'","\n","ev",{"VAR?":"murdered_while_asleep"},{"f()":"reach"},"pop","/ev","\n",{"->":"joe_in_hall.0.g-0"},{"#f":5}]}],{"#f":5}],"c-2":["ev",{"^->":"joe_in_hall.0.found.c-5.9.c-2.$r2"},"/ev",{"temp=":"$r"},{"->":".^.^.2.s"},[{"#n":"$r2"}],"\n","^'But they were disturbed? It's possible.'","\n",{"->":".^.^.^.^.^.g-0"},{"#f":5}]}],{"#f":5}],"c-6":["ev",{"^->":"joe_in_hall.0.found.c-6.$r2"},"/ev",{"temp=":"$r"},{"->":".^.^.6.s"},[{"#n":"$r2"}],"\n","^'All right. It's a start,' Joe replied.","\n",{"->":".^.^.^.g-0.done"},{"->":".^.^.^.g-0"},{"#f":5}],"#f":5,"#n":"found"}],{"g-0":[{"->":".^.^.found"},[["ev",{"VAR?":"joe_wants_better_prints"},{"VAR?":"joe_got_better_prints"},{"f()":"between"},"/ev",{"->":".^.b","c":true},{"b":["\n","ev",{"VAR?":"joe_got_better_prints"},{"f()":"reach"},"pop","/ev","\n","<>","^ 'I'll get those prints from the window now.'","\n",{"->":".^.^.^.3"},null]}],["ev",{"VAR?":"joe_seen_prints_on_knife"},{"f()":"reached"},"/ev",{"->":".^.b","c":true},{"b":["\n","<>","^ 'I'll run those prints as best I can.'","\n",{"->":".^.^.^.3"},null]}],[{"->":".^.b"},{"b":["\n","<>","^ 'Not much to go on.'","\n",{"->":".^.^.^.3"},null]}],"nop","\n","end","end","^ND","\n","^END","\n","^ND","\n","^ND","\n","^END","\n","^ND","\n","^D","\n","^ND","\n","^END","\n","^ND","\n","^ND","\n","^END","\n","^ND","\n","^ND","\n","^ND","\n","^END","\n","^ND","\n","^ND","\n","^ND","\n","^END","\n","^ND","\n","^ND","\n","^END","\n","^ND","\n",{"#f":5,"#n":"done"}],{"#f":5}]}],{"#f":1}],"global decl":["ev",false,{"VAR=":"debug"},0,{"VAR=":"storeClerkID"},1,{"VAR=":"bossManID"},2,{"VAR=":"bartenderID"},{"list":{"Suspects.none":1}},{"VAR=":"Suspects"},{"list":{"Clues.none":1}},{"VAR=":"Clues"},{"list":{},"origins":["knowledge"]},{"VAR=":"knowledge"},{"list":{"items.none":1}},{"VAR=":"items"},"str","^Store Clerk","/str",{"VAR=":"finalSuspect"},0,{"VAR=":"dvisionTotalTime"},false,{"VAR=":"trueEnding"},false,{"VAR=":"confirmedSolution"},false,{"VAR=":"exhaustedOptions"},false,{"VAR=":"startIntro"},false,{"VAR=":"panicked"},false,{"VAR=":"steppedOnGas"},false,{"VAR=":"resignedToFate"},0,{"VAR=":"cluesFoundonBody"},0,{"VAR=":"cluesFoundbyBody"},false,{"VAR=":"talkToPolice"},false,{"VAR=":"talkToPoliceAgain"},false,{"VAR=":"finishedCrimeScene"},false,{"VAR=":"talkedToBossMan"},false,{"VAR=":"isTalkingToPolice"},false,{"VAR=":"canDistract"},false,{"VAR=":"talkedToBartender"},false,{"VAR=":"bartenderToldHisAlibi"},false,{"VAR=":"talkedToCashier"},false,{"VAR=":"cashierToldHisAlibi"},false,{"VAR=":"askedQuestion"},false,{"VAR=":"canEnterStorage"},false,{"VAR=":"talkedToArmchairGuy"},false,{"VAR=":"talkedToSuspiciousGuy"},false,{"VAR=":"SuspiciousGuyAlibi"},false,{"VAR=":"goToPoliceHouse"},false,{"VAR=":"rollCredits"},{"list":{},"origins":["OffOn"]},{"VAR=":"OffOn"},{"list":{},"origins":["SeenUnseen"]},{"VAR=":"SeenUnseen"},{"list":{"GlassState.none":1}},{"VAR=":"GlassState"},{"list":{"BedState.made_up":1}},{"VAR=":"BedState"},{"list":{"Inventory.none":1}},{"VAR=":"Inventory"},{"list":{},"origins":["Supporters"]},{"VAR=":"Supporters"},{"list":{}},{"VAR=":"knowledgeState"},{"list":{"OffOn.off":1,"Supporters.on_desk":1}},{"VAR=":"bedroomLightState"},{"list":{"Supporters.under_bed":4}},{"VAR=":"knifeState"},{"list":{},"origins":["BedKnowledge"]},{"VAR=":"BedKnowledge"},{"list":{},"origins":["KnifeKnowledge"]},{"VAR=":"KnifeKnowledge"},{"list":{},"origins":["WindowKnowledge"]},{"VAR=":"WindowKnowledge"},"/ev","end",null],"#f":1}],"listDefs":{"Suspects":{"none":1,"bossMan":2,"bartender":3,"storeClerk":4},"Clues":{"none":1,"snus":2,"receipts":3,"victimPockets":4,"victimWallet":5,"beer":6,"trisslott":7,"kylarVätska":8,"ratPoison":9,"falafel":10},"knowledge":{"none":1,"victimPoisoned":2,"pocketsEmptied":3,"receiptsBelongToVictim":4,"stoleWallet":5,"knowAboutTrisslott":6,"bartenderAlibi":7,"cashierAlibi":8,"foundCoolantBartender":9,"foundCoolantKiosk":10},"items":{"none":1,"karaokeUSB":2,"beerz":3,"backdoorkey":4},"OffOn":{"off":1,"on":2},"SeenUnseen":{"unseen":1,"seen":2},"GlassState":{"none":1,"steamed":2,"steam_gone":3},"BedState":{"made_up":1,"covers_shifted":2,"covers_off":3,"bloodstain_visible":4},"Inventory":{"none":1,"cane":2,"knife":3},"Supporters":{"on_desk":1,"on_floor":2,"on_bed":3,"under_bed":4,"held":5,"with_joe":6},"BedKnowledge":{"neatly_made":1,"crumpled_duvet":2,"hastily_remade":3,"body_on_bed":4,"murdered_in_bed":5,"murdered_while_asleep":6},"KnifeKnowledge":{"prints_on_knife":1,"joe_seen_prints_on_knife":2,"joe_wants_better_prints":3,"joe_got_better_prints":4},"WindowKnowledge":{"steam_on_glass":1,"fingerprints_on_glass":2,"fingerprints_on_glass_match_knife":3}}}